CHANGES.txt
CONTRIBUTORS.txt
README.txt
ZPL.txt
bibliograph.rendering-configure.zcml
setup.py
bibliograph/__init__.py
bibliograph.rendering.egg-info/PKG-INFO
bibliograph.rendering.egg-info/SOURCES.txt
bibliograph.rendering.egg-info/dependency_links.txt
bibliograph.rendering.egg-info/entry_points.txt
bibliograph.rendering.egg-info/namespace_packages.txt
bibliograph.rendering.egg-info/not-zip-safe
bibliograph.rendering.egg-info/requires.txt
bibliograph.rendering.egg-info/top_level.txt
bibliograph/rendering/README.txt
bibliograph/rendering/TODO.txt
bibliograph/rendering/__init__.py
bibliograph/rendering/configure.zcml
bibliograph/rendering/interfaces.py
bibliograph/rendering/utility.py
bibliograph/rendering/renderers/__init__.py
bibliograph/rendering/renderers/base.py
bibliograph/rendering/renderers/bibtex.py
bibliograph/rendering/renderers/bibtex.txt
bibliograph/rendering/renderers/bibutility.txt
bibliograph/rendering/renderers/endnote.py
bibliograph/rendering/renderers/endnote.txt
bibliograph/rendering/renderers/pdf.py
bibliograph/rendering/renderers/pdf.txt
bibliograph/rendering/renderers/ris.txt
bibliograph/rendering/renderers/utility.txt
bibliograph/rendering/renderers/xml.txt
bibliograph/rendering/renderers/latex_resources/bibmods.sty
bibliograph/rendering/renderers/latex_resources/bibnames.sty
bibliograph/rendering/renderers/latex_resources/showtags.sty
bibliograph/rendering/tests/__init__.py
bibliograph/rendering/tests/test_doctests.py