Metadata-Version: 1.0
Name: bibliograph.rendering
Version: 1.0.0
Summary: Bibliographic renderers
Home-page: http://pypi.python.org/pypi/bibliograph.rendering
Author: Tom Gross
Author-email: itconsense@gmail.com
License: ZPL 2.1
Keywords: bibtex bibliography
Platform: UNKNOWN
Classifier: Framework :: Plone
Classifier: Framework :: Zope2
Classifier: Framework :: Zope3
Classifier: Programming Language :: Python
Classifier: Topic :: Software Development :: Libraries :: Python Modules
Classifier: License :: OSI Approved :: Zope Public License
